idapro_plugin_manager/__init__.py
idapro_plugin_manager-0.1.0.dist-info/METADATA
idapro_plugin_manager-0.1.0.dist-info/WHEEL
idapro_plugin_manager-0.1.0.dist-info/top_level.txt
idapro_plugin_manager-0.1.0.dist-info/RECORD
