Metadata-Version: 2.4
Name: idapro-plugin-manager
Version: 0.1.0
Summary: Plugin Manager for IDA Pro
Author-email: Willi Ballenthin <willi.ballenthin@gmail.com>
License-Expression: Apache-2.0
Keywords: reverse engineering,ida pro,idapro,plugin manager,plugins
Classifier: Development Status :: 3 - Alpha
Classifier: Intended Audience :: Developers
Classifier: Intended Audience :: Information Technology
Classifier: Natural Language :: English
Classifier: Programming Language :: Python :: 3
Classifier: Topic :: Security
Requires-Python: >=3.9
Requires-Dist: importlib-metadata>=8.5.0
Requires-Dist: importlib-resources>=6.5.2
Provides-Extra: build
Requires-Dist: setuptools==78.1.1; extra == "build"
Requires-Dist: build==1.2.2; extra == "build"
